framework16_inputmodule/__init__.py
framework16_inputmodule/cli.py
framework16_inputmodule/font.py
framework16_inputmodule/gui/__init__.py
framework16_inputmodule/gui/games.py
framework16_inputmodule/gui/gui_threading.py
framework16_inputmodule/gui/ledmatrix.py
framework16_inputmodule/inputmodule/__init__.py
framework16_inputmodule/inputmodule/b1display.py
framework16_inputmodule/inputmodule/c1minimal.py
framework16_inputmodule/inputmodule/ledmatrix.py
framework16_inputmodule-0.1.1.dist-info/METADATA
framework16_inputmodule-0.1.1.dist-info/WHEEL
framework16_inputmodule-0.1.1.dist-info/entry_points.txt
framework16_inputmodule-0.1.1.dist-info/RECORD
