Metadata-Version: 2.1
Name: framework16_inputmodule
Version: 0.1.1
Summary: A library to control input modules on the Framework 16 Laptop
Project-URL: Issues, https://github.com/FrameworkComputer/inputmodule-rs/issues
Project-URL: Source, https://github.com/FrameworkComputer/inputmodule-rs
Author-email: Daniel Schaefer <dhs@frame.work>
License: MIT
Keywords: hatch
Classifier: Development Status :: 4 - Beta
Classifier: License :: OSI Approved :: MIT License
Classifier: Programming Language :: Python :: 3
Requires-Python: >=3.7
Requires-Dist: getkey
Requires-Dist: pillow
Requires-Dist: pyserial
Requires-Dist: pysimplegui
